trailerdl/cli.py
trailerdl/settings.json
trailerdl/lib/languages/en.json
trailerdl/lib/scrapers/apple.py
trailerdl/lib/scrapers/tmdb.py
trailerdl/lib/scrapers/youtube.py
trailerdl/lib/tools/download.py
trailerdl/lib/tools/scan.py
trailerdl/lib/tools/search.py
trailerdl/lib/utilities/config.py
trailerdl/lib/utilities/database.py
trailerdl/lib/utilities/logging.py
trailerdl/lib/utilities/matching.py
trailerdl-2.3.dist-info/LICENSE
trailerdl-2.3.dist-info/METADATA
trailerdl-2.3.dist-info/WHEEL
trailerdl-2.3.dist-info/entry_points.txt
trailerdl-2.3.dist-info/top_level.txt
trailerdl-2.3.dist-info/RECORD
